launcher.py
test_acpi.py
test_batteries.py
test_bios.py
test_common.py
test_database.py
test_display.py
test_failures.py
test_installer.py
test_kernel.py
test_launcher.py
test_prerequisites.py
test_pstate.py
test_s2idle.py
test_sleep_report.py
test_ttm.py
test_validator.py
test_wake.py
amd_debug/__init__.py
amd_debug/acpi.py
amd_debug/battery.py
amd_debug/bios.py
amd_debug/common.py
amd_debug/database.py
amd_debug/display.py
amd_debug/failures.py
amd_debug/installer.py
amd_debug/kernel.py
amd_debug/prerequisites.py
amd_debug/pstate.py
amd_debug/s2idle-hook
amd_debug/s2idle.py
amd_debug/sleep_report.py
amd_debug/ttm.py
amd_debug/validator.py
amd_debug/wake.py
amd_debug/bash/amd-s2idle
amd_debug/templates/html
amd_debug/templates/md
amd_debug/templates/stdout
amd_debug/templates/txt
amd_debug_tools-0.2.10.dist-info/licenses/LICENSE
amd_debug_tools-0.2.10.dist-info/METADATA
amd_debug_tools-0.2.10.dist-info/WHEEL
amd_debug_tools-0.2.10.dist-info/entry_points.txt
amd_debug_tools-0.2.10.dist-info/top_level.txt
amd_debug_tools-0.2.10.dist-info/RECORD
