Metadata-Version: 2.4
Name: amd-debug-tools
Version: 0.2.10
Summary: debug tools for AMD systems
Author-email: Mario Limonciello <superm1@kernel.org>
License-Expression: MIT
Project-URL: Homepage, https://web.git.kernel.org/pub/scm/linux/kernel/git/superm1/amd-debug-tools.git/
Classifier: Programming Language :: Python :: 3
Classifier: Operating System :: POSIX :: Linux
Requires-Python: >=3.7
License-File: LICENSE
Requires-Dist: dbus-fast
Requires-Dist: pyudev
Requires-Dist: packaging
Requires-Dist: pandas
Requires-Dist: jinja2
Requires-Dist: tabulate
Requires-Dist: seaborn
Requires-Dist: cysystemd
Requires-Dist: Jinja2
Requires-Dist: matplotlib
Requires-Dist: seaborn
Dynamic: license-file
